[
    {
        "id": 1,
        "name":"Product",
        "price": 200,
        "image": "image/1.png"
    },
    {
        "id": 2,
        "name":"Product",
        "price": 200,
        "image": "image/1.png"
    },
    {
        "id": 3,
        "name":"Product",
        "price": 200,
        "image": "image/1.png"
    },
    {
        "id": 4,
        "name":"Product",
        "price": 200,
        "image": "image/1.png"
    },
    {
        "id": 5,
        "name":"Product",
        "price": 200,
        "image": "image/1.png"
    },
    {
        "id": 6,
        "name":"Product",
        "price": 200,
        "image": "image/1.png"
    },
    {
        "id": 7,
        "name":"Product",
        "price": 200,
        "image": "image/1.png"
    },
    {
        "id": 8,
        "name":"Product",
        "price": 200,
        "image": "image/1.png"
    }

]
